Workbook

Sheet Read Me
A1: Q4 2026 Target & Commercial Model
A3: Purpose: set fair Q4 2026 revenue targets for Property and Jobs inside-sales reps, track the P&L and benchmark pricing.
A4: Method: each rep's Sep-2026 book is projected forward with their trailing churn plus their new-business run-rate, then scaled so the vertical total equals the company goal.
A6: How to use
A7: 1. Change the growth goal (yellow cell) on the Assumptions sheet.
A8: 2. Adjust any blue input on Rep Targets (e.g. a rep's churn) - all targets update.
A10: Colour legend
A11: Blue text = input or data from the pipeline
A12: Black text = formula
A13: Green text = link to another sheet
A14: Yellow fill = key lever to change
A16: Data: synthetic portal data generated by this project (Oct 2024 - Sep 2026). Competitor prices are illustrative.

Sheet Assumptions
A1: Assumptions
A2: Assumption | B2: Value | C2: Source / note
A3: Q4 2026 growth goal vs Q3 2026 | B3: 0.1 | C3: Company goal (config.py)
A4: Property Q3 2026 actual revenue | B4: 9250000 | C4: Pipeline: rep_monthly, Jul-Sep 2026
A5: Jobs Q3 2026 actual revenue | B5: 2305288 | C5: Pipeline: rep_monthly, Jul-Sep 2026
A7: Property Q4 2026 goal | B7: =B4*(1+B3) -> 10175000 | C7: Formula
A8: Jobs Q4 2026 goal | B8: =B5*(1+B3) -> 2535816.8 | C8: Formula
A10: Payment fee rate | B10: 0.025 | C10: Assumption (config.py)
A11: Tech allocation rate | B11: 0.18 | C11: Assumption (config.py)
A13: Average listing utilization (Property, Q3 2026) | B13: 0.601 | C13: Pipeline: account_monthly
A14: Leads per listing per month (Q3 2026) | B14: 3.809 | C14: Pipeline: account_monthly

Sheet Rep Targets
A1: Q4 2026 Rep Targets (bottom-up capacity model)
A3: Rep | B3: Vertical | C3: Sep-26 book revenue | D3: Trailing monthly churn | E3: New-business run-rate / month | F3: Expected Oct | G3: Expected Nov | H3: Expected Dec | I3: Expected Q4 | J3: Share of vertical | K3: Q4 target | L3: Target Oct | M3: Target Nov | N3: Target Dec
A4: PR01 | B4: Property | C4: 235075 | D4: 0.008 | E4: 7121 | F4: =C4*(1-D4)+E4 -> 240315.4 | G4: =C4*(1-D4)^2+E4*((1-D4)+1) -> 245513.88 | H4: =C4*(1-D4)^3+E4*((1-D4)^2+(1-D4)+1) -> 250670.77 | I4: =SUM(F4:H4) -> 736500.04 | J4: =IFERROR(I4/SUMIF($B$4:$B$21,B4,$I$4:$I$21),0) -> 0.075285719 | K4: =J4*IF(B4="Property",Assumptions!$B$7,Assumptions!$B$8) -> 766032.19 | L4: =IFERROR(K4*F4/I4,0) -> 249951.56 | M4: =IFERROR(K4*G4/I4,0) -> 255358.48 | N4: =IFERROR(K4*H4/I4,0) -> 260722.15
A5: PR02 | B5: Property | C5: 263300 | D5: 0.0181 | E5: 7767 | F5: =C5*(1-D5)+E5 -> 266301.27 | G5: =C5*(1-D5)^2+E5*((1-D5)+1) -> 269248.22 | H5: =C5*(1-D5)^3+E5*((1-D5)^2+(1-D5)+1) -> 272141.82 | I5: =SUM(F5:H5) -> 807691.31 | J5: =IFERROR(I5/SUMIF($B$4:$B$21,B5,$I$4:$I$21),0) -> 0.082562957 | K5: =J5*IF(B5="Property",Assumptions!$B$7,Assumptions!$B$8) -> 840078.09 | L5: =IFERROR(K5*F5/I5,0) -> 276979.41 | M5: =IFERROR(K5*G5/I5,0) -> 280044.52 | N5: =IFERROR(K5*H5/I5,0) -> 283054.16
A6: PR03 | B6: Property | C6: 271825 | D6: 0.0101 | E6: 6454 | F6: =C6*(1-D6)+E6 -> 275533.57 | G6: =C6*(1-D6)^2+E6*((1-D6)+1) -> 279204.68 | H6: =C6*(1-D6)^3+E6*((1-D6)^2+(1-D6)+1) -> 282838.71 | I6: =SUM(F6:H6) -> 837576.96 | J6: =IFERROR(I6/SUMIF($B$4:$B$21,B6,$I$4:$I$21),0) -> 0.085617895 | K6: =J6*IF(B6="Property",Assumptions!$B$7,Assumptions!$B$8) -> 871162.09 | L6: =IFERROR(K6*F6/I6,0) -> 286581.9 | M6: =IFERROR(K6*G6/I6,0) -> 290400.22 | N6: =IFERROR(K6*H6/I6,0) -> 294179.97
A7: PR04 | B7: Property | C7: 158200 | D7: 0.0108 | E7: 4450 | F7: =C7*(1-D7)+E7 -> 160941.44 | G7: =C7*(1-D7)^2+E7*((1-D7)+1) -> 163653.27 | H7: =C7*(1-D7)^3+E7*((1-D7)^2+(1-D7)+1) -> 166335.82 | I7: =SUM(F7:H7) -> 490930.53 | J7: =IFERROR(I7/SUMIF($B$4:$B$21,B7,$I$4:$I$21),0) -> 0.050183375 | K7: =J7*IF(B7="Property",Assumptions!$B$7,Assumptions!$B$8) -> 510615.84 | L7: =IFERROR(K7*F7/I7,0) -> 167394.86 | M7: =IFERROR(K7*G7/I7,0) -> 170215.44 | N7: =IFERROR(K7*H7/I7,0) -> 173005.54
A8: PR05 | B8: Property | C8: 280550 | D8: 0.0267 | E8: 9650 | F8: =C8*(1-D8)+E8 -> 282709.32 | G8: =C8*(1-D8)^2+E8*((1-D8)+1) -> 284810.98 | H8: =C8*(1-D8)^3+E8*((1-D8)^2+(1-D8)+1) -> 286856.52 | I8: =SUM(F8:H8) -> 854376.81 | J8: =IFERROR(I8/SUMIF($B$4:$B$21,B8,$I$4:$I$21),0) -> 0.087335192 | K8: =J8*IF(B8="Property",Assumptions!$B$7,Assumptions!$B$8) -> 888635.58 | L8: =IFERROR(K8*F8/I8,0) -> 294045.38 | M8: =IFERROR(K8*G8/I8,0) -> 296231.32 | N8: =IFERROR(K8*H8/I8,0) -> 298358.89
A9: PR06 | B9: Property | C9: 216900 | D9: 0.0217 | E9: 5358 | F9: =C9*(1-D9)+E9 -> 217551.27 | G9: =C9*(1-D9)^2+E9*((1-D9)+1) -> 218188.41 | H9: =C9*(1-D9)^3+E9*((1-D9)^2+(1-D9)+1) -> 218811.72 | I9: =SUM(F9:H9) -> 654551.4 | J9: =IFERROR(I9/SUMIF($B$4:$B$21,B9,$I$4:$I$21),0) -> 0.066908852 | K9: =J9*IF(B9="Property",Assumptions!$B$7,Assumptions!$B$8) -> 680797.57 | L9: =IFERROR(K9*F9/I9,0) -> 226274.63 | M9: =IFERROR(K9*G9/I9,0) -> 226937.32 | N9: =IFERROR(K9*H9/I9,0) -> 227585.62
A10: PR07 | B10: Property | C10: 412500 | D10: 0.0287 | E10: 12512 | F10: =C10*(1-D10)+E10 -> 413173.25 | G10: =C10*(1-D10)^2+E10*((1-D10)+1) -> 413827.18 | H10: =C10*(1-D10)^3+E10*((1-D10)^2+(1-D10)+1) -> 414462.34 | I10: =SUM(F10:H10) -> 1241462.8 | J10: =IFERROR(I10/SUMIF($B$4:$B$21,B10,$I$4:$I$21),0) -> 0.12690348 | K10: =J10*IF(B10="Property",Assumptions!$B$7,Assumptions!$B$8) -> 1291242.9 | L10: =IFERROR(K10*F10/I10,0) -> 429740.66 | M10: =IFERROR(K10*G10/I10,0) -> 430420.8 | N10: =IFERROR(K10*H10/I10,0) -> 431081.43
A11: PR08 | B11: Property | C11: 270150 | D11: 0.0108 | E11: 8879 | F11: =C11*(1-D11)+E11 -> 276111.38 | G11: =C11*(1-D11)^2+E11*((1-D11)+1) -> 282008.38 | H11: =C11*(1-D11)^3+E11*((1-D11)^2+(1-D11)+1) -> 287841.69 | I11: =SUM(F11:H11) -> 845961.44 | J11: =IFERROR(I11/SUMIF($B$4:$B$21,B11,$I$4:$I$21),0) -> 0.086474965 | K11: =J11*IF(B11="Property",Assumptions!$B$7,Assumptions!$B$8) -> 879882.77 | L11: =IFERROR(K11*F11/I11,0) -> 287182.88 | M11: =IFERROR(K11*G11/I11,0) -> 293316.34 | N11: =IFERROR(K11*H11/I11,0) -> 299383.55
A12: PR09 | B12: Property | C12: 322900 | D12: 0.014 | E12: 7354 | F12: =C12*(1-D12)+E12 -> 325733.4 | G12: =C12*(1-D12)^2+E12*((1-D12)+1) -> 328527.13 | H12: =C12*(1-D12)^3+E12*((1-D12)^2+(1-D12)+1) -> 331281.75 | I12: =SUM(F12:H12) -> 985542.28 | J12: =IFERROR(I12/SUMIF($B$4:$B$21,B12,$I$4:$I$21),0) -> 0.10074305 | K12: =J12*IF(B12="Property",Assumptions!$B$7,Assumptions!$B$8) -> 1025060.5 | L12: =IFERROR(K12*F12/I12,0) -> 338794.65 | M12: =IFERROR(K12*G12/I12,0) -> 341700.4 | N12: =IFERROR(K12*H12/I12,0) -> 344565.48
A13: PR10 | B13: Property | C13: 292200 | D13: 0.0262 | E13: 12608 | F13: =C13*(1-D13)+E13 -> 297152.36 | G13: =C13*(1-D13)^2+E13*((1-D13)+1) -> 301974.97 | H13: =C13*(1-D13)^3+E13*((1-D13)^2+(1-D13)+1) -> 306671.22 | I13: =SUM(F13:H13) -> 905798.55 | J13: =IFERROR(I13/SUMIF($B$4:$B$21,B13,$I$4:$I$21),0) -> 0.09259157 | K13: =J13*IF(B13="Property",Assumptions!$B$7,Assumptions!$B$8) -> 942119.23 | L13: =IFERROR(K13*F13/I13,0) -> 309067.56 | M13: =IFERROR(K13*G13/I13,0) -> 314083.55 | N13: =IFERROR(K13*H13/I13,0) -> 318968.12
A14: PR11 | B14: Property | C14: 301500 | D14: 0.0059 | E14: 6075 | F14: =C14*(1-D14)+E14 -> 305796.15 | G14: =C14*(1-D14)^2+E14*((1-D14)+1) -> 310066.95 | H14: =C14*(1-D14)^3+E14*((1-D14)^2+(1-D14)+1) -> 314312.56 | I14: =SUM(F14:H14) -> 930175.66 | J14: =IFERROR(I14/SUMIF($B$4:$B$21,B14,$I$4:$I$21),0) -> 0.095083421 | K14: =J14*IF(B14="Property",Assumptions!$B$7,Assumptions!$B$8) -> 967473.81 | L14: =IFERROR(K14*F14/I14,0) -> 318057.95 | M14: =IFERROR(K14*G14/I14,0) -> 322500.01 | N14: =IFERROR(K14*H14/I14,0) -> 326915.85
A15: PR12 | B15: Property | C15: 166400 | D15: 0.0222 | E15: 2504 | F15: =C15*(1-D15)+E15 -> 165209.92 | G15: =C15*(1-D15)^2+E15*((1-D15)+1) -> 164046.26 | H15: =C15*(1-D15)^3+E15*((1-D15)^2+(1-D15)+1) -> 162908.43 | I15: =SUM(F15:H15) -> 492164.61 | J15: =IFERROR(I15/SUMIF($B$4:$B$21,B15,$I$4:$I$21),0) -> 0.050309524 | K15: =J15*IF(B15="Property",Assumptions!$B$7,Assumptions!$B$8) -> 511899.41 | L15: =IFERROR(K15*F15/I15,0) -> 171834.5 | M15: =IFERROR(K15*G15/I15,0) -> 170624.18 | N15: =IFERROR(K15*H15/I15,0) -> 169440.73
... A21: JR06 | B21: Jobs | C21: 207369 | D21: 0.0278 | E21: 2428 | F21: =C21*(1-D21)+E21 -> 204032.14 | G21: =C21*(1-D21)^2+E21*((1-D21)+1) -> 200788.05 | H21: =C21*(1-D21)^3+E21*((1-D21)^2+(1-D21)+1) -> 197634.14 | I21: =SUM(F21:H21) -> 602454.33 | J21: =IFERROR(I21/SUMIF($B$4:$B$21,B21,$I$4:$I$21),0) -> 0.25004547 | K21: =J21*IF(B21="Property",Assumptions!$B$7,Assumptions!$B$8) -> 634069.49 | L21: =IFERROR(K21*F21/I21,0) -> 214739.19 | M21: =IFERROR(K21*G21/I21,0) -> 211324.86 | N21: =IFERROR(K21*H21/I21,0) -> 208005.44
A23: Total Property | B23: Property | C23: =SUMIF($B$4:$B$21,$B23,C$4:C$21) -> 3191500 | F23: =SUMIF($B$4:$B$21,$B23,F$4:F$21) -> 3226528.7 | G23: =SUMIF($B$4:$B$21,$B23,G$4:G$21) -> 3261070.3 | H23: =SUMIF($B$4:$B$21,$B23,H$4:H$21) -> 3295133.4 | I23: =SUMIF($B$4:$B$21,$B23,I$4:I$21) -> 9782732.4 | K23: =SUMIF($B$4:$B$21,$B23,K$4:K$21) -> 10175000 | L23: =SUMIF($B$4:$B$21,$B23,L$4:L$21) -> 3355905.9 | M23: =SUMIF($B$4:$B$21,$B23,M$4:M$21) -> 3391832.6 | N23: =SUMIF($B$4:$B$21,$B23,N$4:N$21) -> 3427261.5
A24: Total Jobs | B24: Jobs | C24: =SUMIF($B$4:$B$21,$B24,C$4:C$21) -> 789160 | F24: =SUMIF($B$4:$B$21,$B24,F$4:F$21) -> 796222.4 | G24: =SUMIF($B$4:$B$21,$B24,G$4:G$21) -> 803165.39 | H24: =SUMIF($B$4:$B$21,$B24,H$4:H$21) -> 809991.36 | I24: =SUMIF($B$4:$B$21,$B24,I$4:I$21) -> 2409379.1 | K24: =SUMIF($B$4:$B$21,$B24,K$4:K$21) -> 2535816.8 | L24: =SUMIF($B$4:$B$21,$B24,L$4:L$21) -> 838005.98 | M24: =SUMIF($B$4:$B$21,$B24,M$4:M$21) -> 845313.32 | N24: =SUMIF($B$4:$B$21,$B24,N$4:N$21) -> 852497.5
A26: Check: targets equal goal | K26: =IF(ABS(K23-Assumptions!B7)+ABS(K24-Assumptions!B8)<1,"OK","CHECK") -> OK

Sheet Q3 Backtest
A1: Q3 2026 Backtest: legacy equal-split vs bottom-up targets
A3: Rep | B3: Vertical | C3: Actual Q3 | D3: Legacy target | E3: Bottom-up target | F3: Legacy attainment | G3: Bottom-up attainment
A4: PR07 | B4: Property | C4: 1208875 | D4: 832905 | E4: 1330271 | F4: =C4/D4 -> 1.451396 | G4: =C4/E4 -> 0.90874341
A5: PR09 | B5: Property | C5: 923175 | D5: 832905 | E5: 969399 | F5: =C5/D5 -> 1.1083797 | G5: =C5/E5 -> 0.95231685
A6: PR11 | B6: Property | C6: 879075 | D6: 832905 | E6: 984369 | F6: =C6/D6 -> 1.0554325 | G6: =C6/E6 -> 0.89303401
A7: PR03 | B7: Property | C7: 807075 | D7: 832905 | E7: 888327 | F7: =C7/D7 -> 0.96898806 | G7: =C7/E7 -> 0.90853368
A8: PR05 | B8: Property | C8: 795525 | D8: 832905 | E8: 848991 | F8: =C8/D8 -> 0.95512093 | G8: =C8/E8 -> 0.93702407
A9: PR08 | B9: Property | C9: 790600 | D9: 832905 | E9: 876201 | F9: =C9/D9 -> 0.94920789 | G9: =C9/E9 -> 0.90230438
A10: PR10 | B10: Property | C10: 787350 | D10: 832905 | E10: 756315 | F10: =C10/D10 -> 0.94530589 | G10: =C10/E10 -> 1.0410345
A11: PR02 | B11: Property | C11: 782925 | D11: 832905 | E11: 831520 | F11: =C11/D11 -> 0.93999316 | G11: =C11/E11 -> 0.94155883
A12: PR01 | B12: Property | C12: 687650 | D12: 832905 | E12: 745695 | F12: =C12/D12 -> 0.82560436 | G12: =C12/E12 -> 0.92215986
A13: PR06 | B13: Property | C13: 638950 | D13: 832905 | E13: 741376 | F13: =C13/D13 -> 0.76713431 | G13: =C13/E13 -> 0.86184338
A14: PR12 | B14: Property | C14: 491800 | D14: 832905 | E14: 536147 | F14: =C14/D14 -> 0.5904635 | G14: =C14/E14 -> 0.91728574
A15: PR04 | B15: Property | C15: 457000 | D15: 832905 | E15: 486250 | F15: =C15/D15 -> 0.54868202 | G15: =C15/E15 -> 0.93984576
... A21: JR03 | B21: Jobs | C21: 182450 | D21: 423648 | E21: 176301 | F21: =C21/D21 -> 0.43066414 | G21: =C21/E21 -> 1.0348779
A23: Min attainment | F23: =MIN(F4:F21) -> 0.43066414 | G23: =MIN(G4:G21) -> 0.86184338
A24: Max attainment | F24: =MAX(F4:F21) -> 1.4737329 | G24: =MAX(G4:G21) -> 1.0410345
A25: Std deviation | F25: =STDEV(F4:F21) -> 0.30331587 | G25: =STDEV(G4:G21) -> 0.04755674
A26: Reps within +/-10% | F26: =COUNTIFS(F4:F21,">=0.9",F4:F21,"<=1.1")/COUNT(F4:F21) -> 0.38888889 | G26: =COUNTIFS(G4:G21,">=0.9",G4:G21,"<=1.1")/COUNT(G4:G21) -> 0.72222222

Sheet P&L
A1: Monthly P&L by vertical (last 12 months)
A3: Property (AED) | B3: 2025-10 | C3: 2025-11 | D3: 2025-12 | E3: 2026-01 | F3: 2026-02 | G3: 2026-03 | H3: 2026-04 | I3: 2026-05 | J3: 2026-06 | K3: 2026-07 | L3: 2026-08 | M3: 2026-09 | N3: Total
A4: Net revenue | B4: 2523575 | C4: 2604675 | D4: 2631300 | E4: 2697225 | F4: 2786700 | G4: 2881925 | H4: 2958350 | I4: 2981600 | J4: 2984025 | K4: 3010300 | L4: 3048200 | M4: 3191500 | N4: =SUM(B4:M4) -> 34299375
A5: Payment fees | B5: =B4*Assumptions!$B$10 -> 63089.375 | C5: =C4*Assumptions!$B$10 -> 65116.875 | D5: =D4*Assumptions!$B$10 -> 65782.5 | E5: =E4*Assumptions!$B$10 -> 67430.625 | F5: =F4*Assumptions!$B$10 -> 69667.5 | G5: =G4*Assumptions!$B$10 -> 72048.125 | H5: =H4*Assumptions!$B$10 -> 73958.75 | I5: =I4*Assumptions!$B$10 -> 74540 | ... M5: =M4*Assumptions!$B$10 -> 79787.5 | N5: =SUM(B5:M5) -> 857484.38
A6: Tech allocation | B6: =B4*Assumptions!$B$11 -> 454243.5 | C6: =C4*Assumptions!$B$11 -> 468841.5 | D6: =D4*Assumptions!$B$11 -> 473634 | E6: =E4*Assumptions!$B$11 -> 485500.5 | F6: =F4*Assumptions!$B$11 -> 501606 | G6: =G4*Assumptions!$B$11 -> 518746.5 | H6: =H4*Assumptions!$B$11 -> 532503 | I6: =I4*Assumptions!$B$11 -> 536688 | ... M6: =M4*Assumptions!$B$11 -> 574470 | N6: =SUM(B6:M6) -> 6173887.5
A7: Sales team cost | B7: 168000 | C7: 168000 | D7: 168000 | E7: 168000 | F7: 168000 | G7: 168000 | H7: 168000 | I7: 168000 | J7: 168000 | K7: 168000 | L7: 168000 | M7: 168000 | N7: =SUM(B7:M7) -> 2016000
A8: Commissions | B8: 27742 | C8: 34702 | D8: 31065 | E8: 32708 | F8: 39818 | G8: 34628 | H8: 35948 | I8: 24345 | J8: 15645 | K8: 17505 | L8: 26265 | M8: 43612 | N8: =SUM(B8:M8) -> 363983
A9: Marketing spend | B9: 311700 | C9: 365700 | D9: 365300 | E9: 307700 | F9: 299400 | G9: 342300 | H9: 289400 | I9: 294800 | J9: 335700 | K9: 272800 | L9: 322600 | M9: 321200 | N9: =SUM(B9:M9) -> 3828600
A10: Contribution | B10: =B4-SUM(B5:B9) -> 1498800.1 | C10: =C4-SUM(C5:C9) -> 1502314.6 | D10: =D4-SUM(D5:D9) -> 1527518.5 | E10: =E4-SUM(E5:E9) -> 1635885.9 | F10: =F4-SUM(F5:F9) -> 1708208.5 | G10: =G4-SUM(G5:G9) -> 1746202.4 | H10: =H4-SUM(H5:H9) -> 1858540.2 | I10: =I4-SUM(I5:I9) -> 1883227 | ... M10: =M4-SUM(M5:M9) -> 2004430.5 | N10: =SUM(B10:M10) -> 21059420
A11: Contribution margin | B11: =IFERROR(B10/B4,0) -> 0.59391939 | C11: =IFERROR(C10/C4,0) -> 0.57677623 | D11: =IFERROR(D10/D4,0) -> 0.58051856 | E11: =IFERROR(E10/E4,0) -> 0.60650701 | F11: =IFERROR(F10/F4,0) -> 0.61298615 | G11: =IFERROR(G10/G4,0) -> 0.60591527 | H11: =IFERROR(H10/H4,0) -> 0.62823542 | I11: =IFERROR(I10/I4,0) -> 0.63161625 | ... N11: =IFERROR(N10/N4,0) -> 0.61398845
A14: Jobs (AED) | B14: 2025-10 | C14: 2025-11 | D14: 2025-12 | E14: 2026-01 | F14: 2026-02 | G14: 2026-03 | H14: 2026-04 | I14: 2026-05 | J14: 2026-06 | K14: 2026-07 | L14: 2026-08 | M14: 2026-09 | N14: Total
A15: Net revenue | B15: 687542 | C15: 701139 | D15: 698916 | E15: 743417 | F15: 727975 | G15: 728350 | H15: 743525 | I15: 773712 | J15: 752308 | K15: 750478 | L15: 765649 | M15: 789161 | N15: =SUM(B15:M15) -> 8862172
A16: Payment fees | B16: =B15*Assumptions!$B$10 -> 17188.55 | C16: =C15*Assumptions!$B$10 -> 17528.475 | D16: =D15*Assumptions!$B$10 -> 17472.9 | E16: =E15*Assumptions!$B$10 -> 18585.425 | F16: =F15*Assumptions!$B$10 -> 18199.375 | G16: =G15*Assumptions!$B$10 -> 18208.75 | H16: =H15*Assumptions!$B$10 -> 18588.125 | I16: =I15*Assumptions!$B$10 -> 19342.8 | ... M16: =M15*Assumptions!$B$10 -> 19729.025 | N16: =SUM(B16:M16) -> 221554.3
A17: Tech allocation | B17: =B15*Assumptions!$B$11 -> 123757.56 | C17: =C15*Assumptions!$B$11 -> 126205.02 | D17: =D15*Assumptions!$B$11 -> 125804.88 | E17: =E15*Assumptions!$B$11 -> 133815.06 | F17: =F15*Assumptions!$B$11 -> 131035.5 | G17: =G15*Assumptions!$B$11 -> 131103 | H17: =H15*Assumptions!$B$11 -> 133834.5 | I17: =I15*Assumptions!$B$11 -> 139268.16 | ... M17: =M15*Assumptions!$B$11 -> 142048.98 | N17: =SUM(B17:M17) -> 1595191
A18: Sales team cost | B18: 84000 | C18: 84000 | D18: 84000 | E18: 84000 | F18: 84000 | G18: 84000 | H18: 84000 | I18: 84000 | J18: 84000 | K18: 84000 | L18: 84000 | M18: 84000 | N18: =SUM(B18:M18) -> 1008000
A19: Commissions | B19: 11103 | C19: 5991 | D19: 4162 | E19: 8373 | F19: 7165 | G19: 5859 | H19: 7189 | I19: 11818 | J19: 4666 | K19: 4689 | L19: 6228 | M19: 8548 | N19: =SUM(B19:M19) -> 85791
A20: Marketing spend | B20: 100400 | C20: 102200 | D20: 94500 | E20: 95900 | F20: 96400 | G20: 98500 | H20: 95300 | I20: 88800 | J20: 95400 | K20: 92600 | L20: 92900 | M20: 107000 | N20: =SUM(B20:M20) -> 1159900
A21: Contribution | B21: =B15-SUM(B16:B20) -> 351092.89 | C21: =C15-SUM(C16:C20) -> 365214.51 | D21: =D15-SUM(D16:D20) -> 372976.22 | E21: =E15-SUM(E16:E20) -> 402743.52 | F21: =F15-SUM(F16:F20) -> 391175.12 | G21: =G15-SUM(G16:G20) -> 390679.25 | H21: =H15-SUM(H16:H20) -> 404613.38 | I21: =I15-SUM(I16:I20) -> 430483.04 | ... M21: =M15-SUM(M16:M20) -> 427834.99 | N21: =SUM(B21:M21) -> 4791735.7
A22: Contribution margin | B22: =IFERROR(B21/B15,0) -> 0.51064937 | C22: =IFERROR(C21/C15,0) -> 0.52088745 | D22: =IFERROR(D21/D15,0) -> 0.53364957 | E22: =IFERROR(E21/E15,0) -> 0.54174644 | F22: =IFERROR(F21/F15,0) -> 0.53734692 | G22: =IFERROR(G21/G15,0) -> 0.53638944 | H22: =IFERROR(H21/H15,0) -> 0.54418261 | I22: =IFERROR(I21/I15,0) -> 0.55638667 | ... N22: =IFERROR(N21/N15,0) -> 0.54069541

Sheet Pricing
A1: Cost-per-lead benchmark, Q3 2026 (illustrative competitor data)
A3: Portal | B3: Tier | C3: Monthly price | D3: Listing credits | E3: Lead index | F3: Leads / month | G3: Cost per lead | H3: vs our portal
A4: Competitor A | B4: Entry | C4: 3360 | D4: 25 | E4: 0.78 | F4: =D4*Assumptions!$B$13*Assumptions!$B$14*E4 -> 44.639575 | G4: =IFERROR(C4/F4,0) -> 75.269533 | H4: =IFERROR(G4/SUMIFS($G$4:$G$12,$A$4:$A$12,"Our Portal",$B$4:$B$12,B4)-1,0) -> 0.23076923
A5: Competitor B | B5: Entry | C5: 4100 | D5: 30 | E5: 0.92 | F5: =D5*Assumptions!$B$13*Assumptions!$B$14*E5 -> 63.182168 | G5: =IFERROR(C5/F5,0) -> 64.891727 | H5: =IFERROR(G5/SUMIFS($G$4:$G$12,$A$4:$A$12,"Our Portal",$B$4:$B$12,B5)-1,0) -> 0.061076605
A6: Our Portal | B6: Entry | C6: 3500 | D6: 25 | E6: 1 | F6: =D6*Assumptions!$B$13*Assumptions!$B$14*E6 -> 57.230225 | G6: =IFERROR(C6/F6,0) -> 61.156496 | H6: =IFERROR(G6/SUMIFS($G$4:$G$12,$A$4:$A$12,"Our Portal",$B$4:$B$12,B6)-1,0) -> 0
A7: Competitor A | B7: Mid | C7: 7240 | D7: 55 | E7: 0.78 | F7: =D7*Assumptions!$B$13*Assumptions!$B$14*E7 -> 98.207066 | G7: =IFERROR(C7/F7,0) -> 73.721783 | H7: =IFERROR(G7/SUMIFS($G$4:$G$12,$A$4:$A$12,"Our Portal",$B$4:$B$12,B7)-1,0) -> 0.35011655
A8: Competitor B | B8: Mid | C8: 8820 | D8: 70 | E8: 0.92 | F8: =D8*Assumptions!$B$13*Assumptions!$B$14*E8 -> 147.42506 | G8: =IFERROR(C8/F8,0) -> 59.827007 | H8: =IFERROR(G8/SUMIFS($G$4:$G$12,$A$4:$A$12,"Our Portal",$B$4:$B$12,B8)-1,0) -> 0.095652174
A9: Our Portal | B9: Mid | C9: 7500 | D9: 60 | E9: 1 | F9: =D9*Assumptions!$B$13*Assumptions!$B$14*E9 -> 137.35254 | G9: =IFERROR(C9/F9,0) -> 54.604014 | H9: =IFERROR(G9/SUMIFS($G$4:$G$12,$A$4:$A$12,"Our Portal",$B$4:$B$12,B9)-1,0) -> 0
A10: Competitor A | B10: Top | C10: 14180 | D10: 120 | E10: 0.78 | F10: =D10*Assumptions!$B$13*Assumptions!$B$14*E10 -> 214.26996 | G10: =IFERROR(C10/F10,0) -> 66.178198 | H10: =IFERROR(G10/SUMIFS($G$4:$G$12,$A$4:$A$12,"Our Portal",$B$4:$B$12,B10)-1,0) -> 0.51495726
A11: Competitor B | B11: Top | C11: 18380 | D11: 180 | E11: 0.92 | F11: =D11*Assumptions!$B$13*Assumptions!$B$14*E11 -> 379.09301 | G11: =IFERROR(C11/F11,0) -> 48.484144 | H11: =IFERROR(G11/SUMIFS($G$4:$G$12,$A$4:$A$12,"Our Portal",$B$4:$B$12,B11)-1,0) -> 0.10990338
A12: Our Portal | B12: Top | C12: 15000 | D12: 150 | E12: 1 | F12: =D12*Assumptions!$B$13*Assumptions!$B$14*E12 -> 343.38135 | G12: =IFERROR(C12/F12,0) -> 43.683211 | H12: =IFERROR(G12/SUMIFS($G$4:$G$12,$A$4:$A$12,"Our Portal",$B$4:$B$12,B12)-1,0) -> 0
